estiloWidgets/__init__.py
estiloWidgets/autcomplety.py
estiloWidgets/buttonStyle.py
estiloWidgets/entryPlaceHolder.py
estiloWidgets/gradienteFrame.py
estiloWidgets/labelStyle.py
estiloWidgets-0.1.1.dist-info/LICENSE
estiloWidgets-0.1.1.dist-info/METADATA
estiloWidgets-0.1.1.dist-info/WHEEL
estiloWidgets-0.1.1.dist-info/top_level.txt
estiloWidgets-0.1.1.dist-info/RECORD
